qsettingswidget/__init__.py
qsettingswidget/converters/__init__.py
qsettingswidget/converters/converter.py
qsettingswidget/converters/qcheckbox_converter.py
qsettingswidget/converters/simple_converter.py
qsettingswidget/model/__init__.py
qsettingswidget/model/settings_field_node.py
qsettingswidget/model/settings_group_nodel.py
qsettingswidget/model/settings_node.py
qsettingswidget/widgets/__init__.py
qsettingswidget/widgets/q_settings_widget.py
python_qsettingswidget-0.1.0.dist-info/LICENSE
python_qsettingswidget-0.1.0.dist-info/METADATA
python_qsettingswidget-0.1.0.dist-info/WHEEL
python_qsettingswidget-0.1.0.dist-info/top_level.txt
python_qsettingswidget-0.1.0.dist-info/RECORD
